{
    "events": [
        {
            "date" : "2019-10-18",
            "table" : "The Beatles",
            "stats" : [
                {
                    "player" : "Alex",
                    "score" : "78,800"
                },
                {
                    "player" : "Jonny",
                    "score" : "85,580"
                },
                {
                    "player" : "Carlin",
                    "score" : "55,180"
                }
            ]
        }
    ]
}